simple_calc/__init__.py
simple_calc/calc.py
asif_simple_calc-0.0.1.dist-info/LICENSE.txt
asif_simple_calc-0.0.1.dist-info/METADATA
asif_simple_calc-0.0.1.dist-info/WHEEL
asif_simple_calc-0.0.1.dist-info/top_level.txt
asif_simple_calc-0.0.1.dist-info/RECORD
